LICENSE
docs/conf.py
docs/index.rst
docs/requirements.txt
examples/__init__.py
examples/mug_objectron/__init__.py
examples/mug_objectron/demo.py
justpyplot/__init__.py
justpyplot/justpyplot.py
justpyplot/textrender.py
justpyplot-0.2.4.dist-info/METADATA
justpyplot-0.2.4.dist-info/WHEEL
justpyplot-0.2.4.dist-info/licenses/LICENSE
justpyplot-0.2.4.dist-info/RECORD
