Metadata-Version: 2.4
Name: justpyplot
Version: 0.2.4
Summary: Get your plot in you array, plot fast
Author-email: bedbad <antonyuk@bu.edu>
License-File: LICENSE
Classifier: License :: OSI Approved :: GNU General Public License v3 (GPLv3)
Classifier: Operating System :: OS Independent
Classifier: Programming Language :: Python :: 3
Requires-Dist: numpy
Provides-Extra: cv2
Requires-Dist: opencv-python; extra == 'cv2'
Provides-Extra: demo
Requires-Dist: mediapipe; extra == 'demo'
Requires-Dist: scipy; extra == 'demo'
Provides-Extra: dev
Requires-Dist: opencv-python; extra == 'dev'
Requires-Dist: perf-timer; extra == 'dev'
Requires-Dist: ruff>=0.0.279; extra == 'dev'
Provides-Extra: perf-timer
Requires-Dist: perf-timer; extra == 'perf-timer'
Provides-Extra: pil
Requires-Dist: pil; extra == 'pil'
